custom_maya/__init__.py
custom_maya/functions.py
custom_maya/test_open_scene.py
custom_maya/test_temp.py
custom_maya/customclass/__init__.py
custom_maya/customclass/base_class.py
custom_maya/tools/__init__.py
custom_maya-0.2.dist-info/METADATA
custom_maya-0.2.dist-info/WHEEL
custom_maya-0.2.dist-info/top_level.txt
custom_maya-0.2.dist-info/RECORD
