Metadata-Version: 2.1
Name: custom-maya
Version: 0.2
Summary: Maya的便利工具
Author: qiao yuanzhen
Author-email: narutozbjp@hotmail.com
Requires-Python: >3.7
